py3_qunjielong/__init__.py
py3_qunjielong/qunjnielong.py
py3_qunjielong-1.1.4.dist-info/LICENSE
py3_qunjielong-1.1.4.dist-info/METADATA
py3_qunjielong-1.1.4.dist-info/WHEEL
py3_qunjielong-1.1.4.dist-info/top_level.txt
py3_qunjielong-1.1.4.dist-info/RECORD
