Metadata-Version: 2.1
Name: py3-qunjielong
Version: 1.1.4
Summary: The Python3 Qunjielong Library Developed By Guolei
Home-page: https://github.com/guolei19850528/py3_qunjielong
Author: guolei
Author-email: 174000902@qq.com
License: MIT
Requires-Python: >=3.0
License-File: LICENSE
Requires-Dist: py3-requests
Requires-Dist: diskcache
Requires-Dist: redis
Requires-Dist: addict
Requires-Dist: retrying
Requires-Dist: jsonschema
Requires-Dist: setuptools
Requires-Dist: wheel
